tuning_library/__init__.py
tuning_library/_tuning_library.cp38-win32.pyd
tuning_library/tuning_library.cpp
tuning_library-0.1.0.dist-info/METADATA
tuning_library-0.1.0.dist-info/WHEEL
tuning_library-0.1.0.dist-info/licenses/LICENSE
tuning_library-0.1.0.dist-info/RECORD
