Metadata-Version: 2.2
Name: tuning_library
Version: 0.1.0
Summary: Python bindings for the Surge Synth Team Tuning Library
Author: Naren Ratan
License: Copyright 2024, Naren Ratan
Project-URL: Homepage, https://github.com/surge-synthesizer/tuning-library-python
Project-URL: Issues, https://github.com/surge-synthesizer/tuning-library-python/issues
Requires-Python: >=3.8
